XtraCrysPy/Atomic.py
XtraCrysPy/Line2D.py
XtraCrysPy/Model.py
XtraCrysPy/Reciprocal.py
XtraCrysPy/XtraCrysPy.py
XtraCrysPy/__init__.py
XtraCrysPy/conversion.py
XtraCrysPy/cylinder.py
XtraCrysPy/defaults.py
XtraCrysPy/file_io.py
XtraCrysPy/interface.py
XtraCrysPy/iso_surface.py
XtraCrysPy/lattice_format.py
XtraCrysPy-1.1.5.dist-info/LICENSE
XtraCrysPy-1.1.5.dist-info/METADATA
XtraCrysPy-1.1.5.dist-info/WHEEL
XtraCrysPy-1.1.5.dist-info/entry_points.txt
XtraCrysPy-1.1.5.dist-info/top_level.txt
XtraCrysPy-1.1.5.dist-info/RECORD
