Metadata-Version: 2.1
Name: XtraCrysPy
Version: 1.1.5
Summary: A Python tool for visualizing atomic systems and properties of condensed matter.
Home-page: https://github.com/sassafrass6/XtraCrysPy
Author: Frank T. Cerasoli
Author-email: ftcerasoli@ucdavis.edu
Platform: Unix
Requires-Python: >=3.7
License-File: LICENSE
Requires-Dist: ase
Requires-Dist: fury
Requires-Dist: numpy
